{
  "db_name": "PostgreSQL",
  "query": "\n            UPDATE data_plane_private_links SET\n                provider = $2,\n                config = $3,\n                status = 'pending',\n                details = NULL,\n                error = NULL,\n                observed_at = NULL,\n                updated_at = now()\n            WHERE id = $1\n            RETURNING\n                status,\n                details as \"details: sqlx::types::Json<serde_json::Value>\",\n                error,\n                observed_at as \"observed_at: chrono::DateTime<chrono::Utc>\"\n            ",
  "describe": {
    "columns": [
      {
        "ordinal": 0,
        "name": "status",
        "type_info": "Text"
      },
      {
        "ordinal": 1,
        "name": "details: sqlx::types::Json<serde_json::Value>",
        "type_info": "Jsonb"
      },
      {
        "ordinal": 2,
        "name": "error",
        "type_info": "Text"
      },
      {
        "ordinal": 3,
        "name": "observed_at: chrono::DateTime<chrono::Utc>",
        "type_info": "Timestamptz"
      }
    ],
    "parameters": {
      "Left": [
        "Macaddr8",
        "Text",
        "Jsonb"
      ]
    },
    "nullable": [
      false,
      true,
      true,
      true
    ]
  },
  "hash": "83e8089031d4761b394960b40feeab81829d07bcba5ee43cc672e2c6916bcf7a"
}
